kairondb/__init__.py
kairondb/bridge.py
kairondb/cache.py
kairondb/dashboard.py
kairondb/exceptions.py
kairondb/fields.py
kairondb/fields_advanced.py
kairondb/migrations.py
kairondb/models.py
kairondb/optimizations.py
kairondb/pool.py
kairondb/profiling.py
kairondb/query.py
kairondb/sqlbridge.dll
kairondb/sqlbridge.so
kairondb/typing.py
kairondb/utils.py
kairondb/validators.py
kairondb-1.1.0.dist-info/licenses/LICENSE
kairondb-1.1.0.dist-info/METADATA
kairondb-1.1.0.dist-info/WHEEL
kairondb-1.1.0.dist-info/top_level.txt
kairondb-1.1.0.dist-info/RECORD
